tidewave/__init__.py
tidewave/mcp_handler.py
tidewave/middleware.py
tidewave/django/__init__.py
tidewave/django/apps.py
tidewave/django/models.py
tidewave/django/sql.py
tidewave/django/templates.py
tidewave/fastapi/__init__.py
tidewave/fastapi/middleware.py
tidewave/flask/__init__.py
tidewave/flask/middleware.py
tidewave/jinja2/__init__.py
tidewave/sqlalchemy/__init__.py
tidewave/sqlalchemy/models.py
tidewave/sqlalchemy/sql.py
tidewave/tools/__init__.py
tidewave/tools/base.py
tidewave/tools/get_logs.py
tidewave/tools/project_eval.py
tidewave/tools/source.py
tidewave-0.1.2.dist-info/METADATA
tidewave-0.1.2.dist-info/WHEEL
tidewave-0.1.2.dist-info/licenses/LICENSE
tidewave-0.1.2.dist-info/RECORD
