Metadata-Version: 2.4
Name: tidewave
Version: 0.1.2
Summary: Tidewave Web for Django, FastAPI, and Flask
Project-URL: Homepage, https://tidewave.ai
Project-URL: Repository, https://github.com/tidewave-ai/tidewave_python
Project-URL: Issues, https://github.com/tidewave-ai/tidewave_python/issues
License-File: LICENSE
Classifier: Programming Language :: Python :: 3 :: Only
Classifier: Programming Language :: Python :: 3.9
Classifier: Programming Language :: Python :: 3.10
Classifier: Programming Language :: Python :: 3.11
Classifier: Programming Language :: Python :: 3.12
Classifier: Programming Language :: Python :: 3.13
Requires-Python: >=3.9
Requires-Dist: pydantic>=2
Provides-Extra: django
Requires-Dist: django>=4.2; extra == 'django'
Provides-Extra: fastapi
Requires-Dist: a2wsgi>=1.9.0; extra == 'fastapi'
Requires-Dist: fastapi>=0.100; extra == 'fastapi'
Provides-Extra: flask
Requires-Dist: flask>=2; extra == 'flask'
Provides-Extra: sqlalchemy
Requires-Dist: sqlalchemy>=2.0; extra == 'sqlalchemy'
